guessFact/__init__.py
guessFact/__main__.py
guessFact/code.py
guessFact-0.1.1.dist-info/LICENSE
guessFact-0.1.1.dist-info/METADATA
guessFact-0.1.1.dist-info/WHEEL
guessFact-0.1.1.dist-info/entry_points.txt
guessFact-0.1.1.dist-info/top_level.txt
guessFact-0.1.1.dist-info/RECORD
