Metadata-Version: 2.1
Name: guessFact
Version: 0.1.1
Summary: A Python package lets users select a category and sub-category to reveal two unique facts about it. One fact is true, while the other is a playful fabrication, and the user needs to identify the correct one.
Author-email: Hanna Han <mh6161@nyu.edu>, Wilson Xu <wx2105@nyu.edu>, Sewon Kim <sak9725@nyu.edu>, Rhan Chen <xc2344@nyu.edu>
License: GNU GENERAL PUBLIC LICENSE
Project-URL: Repository, https://github.com/software-students-fall2024/3-python-package-thecoders2
Keywords: python,package,build,tutorial
Classifier: Programming Language :: Python :: 3
Classifier: Intended Audience :: Education
Classifier: License :: OSI Approved :: GNU General Public License v3 (GPLv3)
Classifier: Operating System :: OS Independent
Requires-Python: >=3.7
License-File: LICENSE
Provides-Extra: dev
Requires-Dist: pytest; extra == "dev"
